[
    {
        "symbol": "ETH",
        "name": "Ethereum",
        "address": "0x",
        "imageUrl": "https://s2.coinmarketcap.com/static/img/coins/64x64/3513.png",
        "rate": 2650.44,
        "chainId": 1
    },
    {
        "symbol": "rswETH",
        "name": "Ethereum",
        "address": "0xFAe103DC9cf190eD75350761e95403b7b8aFa6c0",
        "imageUrl": "https://wigoswap.io/images/tokens/0x04068DA6C83AFCFA0e13ba15A6696662335D5B75.png",
        "rate": 2678.08,
        "chainId": 1
    },
    {
        "symbol": "swETH",
        "name": "Ethereum",
        "address": "0xf951E335afb289353dc249e82926178EaC7DEd78",
        "imageUrl": "https://wigoswap.io/images/tokens/0x049d68029688eAbF473097a2fC38ef61633A3C7A.png",
        "rate": 2813.06,
        "chainId": 1
    }
]